mcp_id_photo/__init__.py
mcp_id_photo/server.py
mcp_id_photo-1.0.4.dist-info/METADATA
mcp_id_photo-1.0.4.dist-info/WHEEL
mcp_id_photo-1.0.4.dist-info/entry_points.txt
mcp_id_photo-1.0.4.dist-info/RECORD
