Metadata-Version: 2.4
Name: mcp-id-photo
Version: 1.0.4
Summary: MCP服务器：证件照生成工具，提供AI证件照生成功能
Project-URL: Homepage, https://github.com/fengjinchao/mcp-image-super-resolution
Project-URL: Repository, https://github.com/fengjinchao/mcp-image-super-resolution
Project-URL: Documentation, https://github.com/fengjinchao/mcp-image-super-resolution#readme
Project-URL: Issues, https://github.com/fengjinchao/mcp-image-super-resolution/issues
Author-email: fengjinchao <fengjinchao@example.com>
License: MIT
Keywords: ai,aliyun,image,image-enhancement,mcp,super-resolution,upscale
Classifier: Development Status :: 4 - Beta
Classifier: Intended Audience :: Developers
Classifier: License :: OSI Approved :: MIT License
Classifier: Programming Language :: Python :: 3
Classifier: Programming Language :: Python :: 3.10
Classifier: Programming Language :: Python :: 3.11
Classifier: Programming Language :: Python :: 3.12
Classifier: Topic :: Scientific/Engineering :: Artificial Intelligence
Classifier: Topic :: Scientific/Engineering :: Image Processing
Classifier: Topic :: Software Development :: Libraries :: Python Modules
Requires-Python: >=3.10
Requires-Dist: dashscope>=1.23.8
Requires-Dist: mcp[cli]>=1.0.0
Requires-Dist: pillow>=10.4.0
